[{"archiveView":0,"follower":8498,"time":1628094202118},{"archiveView":0,"follower":8507,"time":1628123320434},{"archiveView":0,"follower":8517,"time":1628132889576},{"archiveView":0,"follower":8527,"time":1628143643496},{"archiveView":0,"follower":8537,"time":1628150142299},{"archiveView":0,"follower":8546,"time":1628157809386},{"archiveView":0,"follower":8555,"time":1628163254815},{"archiveView":0,"follower":8566,"time":1628169839200},{"archiveView":0,"follower":8578,"time":1628172075058},{"archiveView":0,"follower":8591,"time":1628174524887},{"archiveView":0,"follower":8602,"time":1628177648294},{"archiveView":0,"follower":8614,"time":1628180822485},{"archiveView":0,"follower":8624,"time":1628186450481},{"archiveView":0,"follower":8633,"time":1628202789947},{"archiveView":0,"follower":8644,"time":1628222173488},{"archiveView":0,"follower":8655,"time":1628234841760},{"archiveView":0,"follower":8664,"time":1628247740116},{"archiveView":0,"follower":8676,"time":1628251047265},{"archiveView":0,"follower":8687,"time":1628252606158},{"archiveView":0,"follower":8701,"time":1628254919561},{"archiveView":0,"follower":8710,"time":1628256347932},{"archiveView":0,"follower":8719,"time":1628257738709},{"archiveView":0,"follower":8732,"time":1628259982457},{"archiveView":0,"follower":8742,"time":1628262983982},{"archiveView":0,"follower":8752,"time":1628266301216},{"archiveView":0,"follower":8761,"time":1628275568182},{"archiveView":0,"follower":8771,"time":1628297259829},{"archiveView":0,"follower":8783,"time":1628301996317},{"archiveView":0,"follower":8796,"time":1628306323297},{"archiveView":0,"follower":8809,"time":1628311958952},{"archiveView":0,"follower":8819,"time":1628315026776},{"archiveView":0,"follower":8830,"time":1628318048850},{"archiveView":0,"follower":8841,"time":1628319093389},{"archiveView":0,"follower":8851,"time":1628321046751},{"archiveView":0,"follower":8860,"time":1628325017763},{"archiveView":0,"follower":8875,"time":1628329083739},{"archiveView":0,"follower":8886,"time":1628332032070},{"archiveView":0,"follower":8901,"time":1628333997414},{"archiveView":0,"follower":8912,"time":1628334943469},{"archiveView":0,"follower":8927,"time":1628335922134},{"archiveView":0,"follower":8937,"time":1628336847433},{"archiveView":0,"follower":8948,"time":1628338490358},{"archiveView":0,"follower":8963,"time":1628339256441},{"archiveView":0,"follower":8973,"time":1628340057820},{"archiveView":0,"follower":8985,"time":1628341700432},{"archiveView":0,"follower":8999,"time":1628343975504},{"archiveView":0,"follower":9015,"time":1628347135082},{"archiveView":0,"follower":9035,"time":1628351867944},{"archiveView":0,"follower":9050,"time":1628354073169},{"archiveView":0,"follower":9068,"time":1628356437931},{"archiveView":0,"follower":9081,"time":1628360823283},{"archiveView":0,"follower":9092,"time":1628382242479},{"archiveView":0,"follower":9102,"time":1628390676101},{"archiveView":0,"follower":9114,"time":1628396047961},{"archiveView":0,"follower":9128,"time":1628402516433},{"archiveView":0,"follower":9139,"time":1628407824228},{"archiveView":0,"follower":9149,"time":1628413520787},{"archiveView":0,"follower":9169,"time":1628416691951},{"archiveView":0,"follower":9181,"time":1628420488339},{"archiveView":0,"follower":9191,"time":1628424978177},{"archiveView":0,"follower":9201,"time":1628428782547},{"archiveView":0,"follower":9211,"time":1628436639150},{"archiveView":0,"follower":9223,"time":1628439289663},{"archiveView":0,"follower":9239,"time":1628441546749},{"archiveView":0,"follower":9249,"time":1628443925520},{"archiveView":0,"follower":9259,"time":1628445218770},{"archiveView":0,"follower":9271,"time":1628448218651},{"archiveView":0,"follower":9281,"time":1628464613603},{"archiveView":0,"follower":9291,"time":1628482797832},{"archiveView":0,"follower":9301,"time":1628489629912},{"archiveView":0,"follower":9312,"time":1628496863913},{"archiveView":0,"follower":9322,"time":1628502882783},{"archiveView":0,"follower":9333,"time":1628505478523},{"archiveView":0,"follower":9344,"time":1628506737703},{"archiveView":0,"follower":9358,"time":1628508927767},{"archiveView":0,"follower":9370,"time":1628509903628},{"archiveView":0,"follower":9383,"time":1628512902949},{"archiveView":0,"follower":9397,"time":1628517686614},{"archiveView":0,"follower":9410,"time":1628519590114},{"archiveView":0,"follower":9421,"time":1628522449776},{"archiveView":0,"follower":9431,"time":1628527837346},{"archiveView":0,"follower":9446,"time":1628531675573},{"archiveView":0,"follower":9456,"time":1628536876095},{"archiveView":0,"follower":9467,"time":1628558630166},{"archiveView":0,"follower":9479,"time":1628567703190},{"archiveView":0,"follower":9490,"time":1628578521941},{"archiveView":0,"follower":9501,"time":1628594516228},{"archiveView":0,"follower":9513,"time":1628597265242},{"archiveView":0,"follower":9527,"time":1628598910249},{"archiveView":0,"follower":9537,"time":1628602376313},{"archiveView":0,"follower":9548,"time":1628604715316},{"archiveView":0,"follower":10627,"time":1628605505478},{"archiveView":0,"follower":10638,"time":1628618089295},{"archiveView":0,"follower":10652,"time":1628619788048},{"archiveView":0,"follower":10664,"time":1628621871008},{"archiveView":0,"follower":10676,"time":1628643939123},{"archiveView":0,"follower":10691,"time":1628651502162},{"archiveView":0,"follower":10702,"time":1628664467788},{"archiveView":0,"follower":10715,"time":1628681177663},{"archiveView":0,"follower":10727,"time":1628686783404},{"archiveView":0,"follower":10739,"time":1628692415010},{"archiveView":0,"follower":10750,"time":1628698310549},{"archiveView":0,"follower":10772,"time":1628703760900},{"archiveView":0,"follower":10786,"time":1628707582455},{"archiveView":0,"follower":10798,"time":1628725850225},{"archiveView":0,"follower":10811,"time":1628744919367},{"archiveView":0,"follower":10823,"time":1628756783788},{"archiveView":0,"follower":10838,"time":1628771239844},{"archiveView":0,"follower":10851,"time":1628774367956},{"archiveView":0,"follower":10863,"time":1628776185713},{"archiveView":0,"follower":10878,"time":1628779169480},{"archiveView":0,"follower":10890,"time":1628780092682},{"archiveView":0,"follower":10913,"time":1628781037195},{"archiveView":0,"follower":10925,"time":1628786137715},{"archiveView":0,"follower":10945,"time":1628790550849},{"archiveView":0,"follower":10963,"time":1628792828984},{"archiveView":0,"follower":10975,"time":1628798703895},{"archiveView":0,"follower":10986,"time":1628858126216},{"archiveView":0,"follower":10997,"time":1628861800935},{"archiveView":0,"follower":11008,"time":1628871725532},{"archiveView":0,"follower":11032,"time":1628874730606},{"archiveView":0,"follower":11044,"time":1628876343634},{"archiveView":0,"follower":11064,"time":1628879772388},{"archiveView":0,"follower":11079,"time":1628885622724},{"archiveView":0,"follower":11092,"time":1628892321852},{"archiveView":0,"follower":11105,"time":1628898760747},{"archiveView":0,"follower":11117,"time":1628901810572},{"archiveView":0,"follower":11130,"time":1628905067162},{"archiveView":0,"follower":11151,"time":1628907772305},{"archiveView":0,"follower":11171,"time":1628912104296},{"archiveView":0,"follower":11190,"time":1628917354342},{"archiveView":0,"follower":11204,"time":1628923806235},{"archiveView":0,"follower":11217,"time":1628933355047},{"archiveView":0,"follower":11229,"time":1628937214046},{"archiveView":0,"follower":11241,"time":1628943910342},{"archiveView":0,"follower":11255,"time":1628953192838},{"archiveView":0,"follower":11269,"time":1628971484034},{"archiveView":0,"follower":11282,"time":1628999829966},{"archiveView":0,"follower":11294,"time":1629015255129},{"archiveView":0,"follower":11307,"time":1629030233051},{"archiveView":0,"follower":11322,"time":1629034733135},{"archiveView":0,"follower":11334,"time":1629039538360},{"archiveView":0,"follower":11349,"time":1629040583969},{"archiveView":0,"follower":11361,"time":1629045457090},{"archiveView":0,"follower":11373,"time":1629050004080},{"archiveView":0,"follower":11390,"time":1629059291415},{"archiveView":0,"follower":11403,"time":1629096075138},{"archiveView":0,"follower":11415,"time":1629110754380},{"archiveView":0,"follower":11429,"time":1629120942417},{"archiveView":0,"follower":11445,"time":1629130092252},{"archiveView":0,"follower":11457,"time":1629136261496},{"archiveView":0,"follower":11469,"time":1629143008996},{"archiveView":0,"follower":11481,"time":1629171713801},{"archiveView":0,"follower":11496,"time":1629183954720},{"archiveView":0,"follower":11508,"time":1629191130385},{"archiveView":0,"follower":11522,"time":1629202800364},{"archiveView":0,"follower":11539,"time":1629210454511},{"archiveView":0,"follower":11553,"time":1629212552522},{"archiveView":0,"follower":11566,"time":1629223117898},{"archiveView":0,"follower":11583,"time":1629229439719},{"archiveView":0,"follower":11619,"time":1629232261037},{"archiveView":0,"follower":11636,"time":1629238241635},{"archiveView":0,"follower":11660,"time":1629243446192},{"archiveView":0,"follower":11674,"time":1629245861584},{"archiveView":0,"follower":11687,"time":1629248295034},{"archiveView":0,"follower":11700,"time":1629250404198},{"archiveView":0,"follower":11716,"time":1629254019405},{"archiveView":0,"follower":11728,"time":1629257363272},{"archiveView":0,"follower":11741,"time":1629262695953},{"archiveView":0,"follower":11754,"time":1629267293532},{"archiveView":0,"follower":11766,"time":1629275930807},{"archiveView":0,"follower":11778,"time":1629280536664},{"archiveView":0,"follower":11793,"time":1629296979584},{"archiveView":0,"follower":11807,"time":1629302371799},{"archiveView":0,"follower":11819,"time":1629305703228},{"archiveView":0,"follower":11831,"time":1629308237199},{"archiveView":0,"follower":11847,"time":1629330418786},{"archiveView":0,"follower":11860,"time":1629337351208},{"archiveView":0,"follower":11878,"time":1629344902745},{"archiveView":0,"follower":11900,"time":1629348113759},{"archiveView":0,"follower":11913,"time":1629350931957},{"archiveView":0,"follower":11930,"time":1629356222120},{"archiveView":0,"follower":11945,"time":1629360612297},{"archiveView":0,"follower":11960,"time":1629367008140},{"archiveView":0,"follower":11973,"time":1629371359668},{"archiveView":0,"follower":11985,"time":1629378056679},{"archiveView":0,"follower":12004,"time":1629383604063},{"archiveView":0,"follower":12019,"time":1629386078745},{"archiveView":0,"follower":12041,"time":1629390339423},{"archiveView":0,"follower":12058,"time":1629395995892},{"archiveView":0,"follower":12072,"time":1629399933682},{"archiveView":0,"follower":12086,"time":1629438237375},{"archiveView":0,"follower":12099,"time":1629456129294},{"archiveView":0,"follower":12113,"time":1629464654176},{"archiveView":0,"follower":12127,"time":1629471494693},{"archiveView":0,"follower":12144,"time":1629476632021},{"archiveView":0,"follower":12168,"time":1629477655152},{"archiveView":0,"follower":12183,"time":1629478723689},{"archiveView":0,"follower":12200,"time":1629481724047},{"archiveView":0,"follower":12223,"time":1629485841078},{"archiveView":0,"follower":12236,"time":1629488200519},{"archiveView":0,"follower":12251,"time":1629496913502},{"archiveView":0,"follower":12272,"time":1629503106999},{"archiveView":0,"follower":12285,"time":1629505751201},{"archiveView":0,"follower":12314,"time":1629510638229},{"archiveView":0,"follower":12341,"time":1629515263380},{"archiveView":0,"follower":12355,"time":1629518252399},{"archiveView":0,"follower":12379,"time":1629523144540},{"archiveView":0,"follower":12398,"time":1629529199771},{"archiveView":0,"follower":12412,"time":1629538141308},{"archiveView":0,"follower":12425,"time":1629547167099},{"archiveView":0,"follower":12443,"time":1629551585615},{"archiveView":0,"follower":12470,"time":1629553278345},{"archiveView":0,"follower":12487,"time":1629555013138},{"archiveView":0,"follower":12500,"time":1629559732560},{"archiveView":0,"follower":12514,"time":1629562705282},{"archiveView":0,"follower":12535,"time":1629567653600},{"archiveView":0,"follower":12549,"time":1629569135672},{"archiveView":0,"follower":12563,"time":1629575642518},{"archiveView":0,"follower":12580,"time":1629597563815},{"archiveView":0,"follower":12593,"time":1629606234768},{"archiveView":0,"follower":12608,"time":1629615936281},{"archiveView":0,"follower":12621,"time":1629625377133},{"archiveView":0,"follower":12635,"time":1629630212749},{"archiveView":0,"follower":12649,"time":1629642885118},{"archiveView":0,"follower":12662,"time":1629650337696},{"archiveView":0,"follower":12678,"time":1629660401564},{"archiveView":0,"follower":12691,"time":1629670309295},{"archiveView":0,"follower":12705,"time":1629689138771},{"archiveView":0,"follower":12719,"time":1629694219024},{"archiveView":0,"follower":12732,"time":1629705804689},{"archiveView":0,"follower":12745,"time":1629720530867},{"archiveView":0,"follower":12758,"time":1629724892915},{"archiveView":0,"follower":12772,"time":1629729325854},{"archiveView":0,"follower":12786,"time":1629731492337},{"archiveView":0,"follower":12803,"time":1629735856593},{"archiveView":0,"follower":12820,"time":1629743731349},{"archiveView":0,"follower":12834,"time":1629774487098},{"archiveView":0,"follower":12847,"time":1629797712022},{"archiveView":0,"follower":12861,"time":1629807136909},{"archiveView":0,"follower":12874,"time":1629812163477},{"archiveView":0,"follower":12887,"time":1629815903403},{"archiveView":0,"follower":12901,"time":1629819977415},{"archiveView":0,"follower":12916,"time":1629826600137},{"archiveView":0,"follower":12929,"time":1629830088135},{"archiveView":0,"follower":12942,"time":1629833531191},{"archiveView":0,"follower":12955,"time":1629839196844},{"archiveView":0,"follower":12970,"time":1629849223592},{"archiveView":0,"follower":12983,"time":1629866723864},{"archiveView":0,"follower":12998,"time":1629885796181},{"archiveView":0,"follower":13013,"time":1629900751803},{"archiveView":0,"follower":13027,"time":1629905833918},{"archiveView":0,"follower":13045,"time":1629909797484},{"archiveView":0,"follower":13064,"time":1629913107350},{"archiveView":0,"follower":13078,"time":1629921986167},{"archiveView":0,"follower":13093,"time":1629950029655},{"archiveView":0,"follower":13110,"time":1629961582036},{"archiveView":0,"follower":13130,"time":1629970168935},{"archiveView":0,"follower":13145,"time":1629984239419},{"archiveView":0,"follower":13160,"time":1630001995742},{"archiveView":0,"follower":13175,"time":1630028142656},{"archiveView":0,"follower":13193,"time":1630049384924},{"archiveView":0,"follower":13207,"time":1630062917608},{"archiveView":0,"follower":13221,"time":1630073627742},{"archiveView":0,"follower":13235,"time":1630102958005},{"archiveView":0,"follower":13249,"time":1630121083460},{"archiveView":0,"follower":13263,"time":1630139313503},{"archiveView":0,"follower":13277,"time":1630151926913},{"archiveView":0,"follower":13300,"time":1630153910553},{"archiveView":0,"follower":13316,"time":1630154808122},{"archiveView":0,"follower":13330,"time":1630155750584},{"archiveView":0,"follower":13346,"time":1630156803135},{"archiveView":0,"follower":13364,"time":1630158831969},{"archiveView":0,"follower":13386,"time":1630161653675},{"archiveView":0,"follower":13401,"time":1630163442854},{"archiveView":0,"follower":13422,"time":1630164564543},{"archiveView":0,"follower":13438,"time":1630165512016},{"archiveView":0,"follower":13454,"time":1630168620447},{"archiveView":0,"follower":13468,"time":1630179892662},{"archiveView":0,"follower":13482,"time":1630207305217},{"archiveView":0,"follower":13498,"time":1630218910722},{"archiveView":0,"follower":13516,"time":1630219927413},{"archiveView":0,"follower":13537,"time":1630221114168},{"archiveView":0,"follower":13554,"time":1630223228617},{"archiveView":0,"follower":13573,"time":1630227937132},{"archiveView":0,"follower":13595,"time":1630232912083},{"archiveView":0,"follower":13626,"time":1630236197175},{"archiveView":0,"follower":13643,"time":1630237424035},{"archiveView":0,"follower":13664,"time":1630239179062},{"archiveView":0,"follower":13830,"time":1630241101290},{"archiveView":0,"follower":13853,"time":1630244400625},{"archiveView":0,"follower":13869,"time":1630247698547},{"archiveView":0,"follower":13884,"time":1630250998442},{"archiveView":0,"follower":13905,"time":1630253368308},{"archiveView":0,"follower":13935,"time":1630256159388},{"archiveView":0,"follower":13954,"time":1630259412066},{"archiveView":0,"follower":13968,"time":1630264978742},{"archiveView":0,"follower":13984,"time":1630282664477},{"archiveView":0,"follower":13998,"time":1630289334985},{"archiveView":0,"follower":14012,"time":1630296064540},{"archiveView":0,"follower":14030,"time":1630306953567},{"archiveView":0,"follower":14046,"time":1630320582471},{"archiveView":0,"follower":14062,"time":1630330702298},{"archiveView":0,"follower":14080,"time":1630339133249},{"archiveView":0,"follower":14095,"time":1630361560402},{"archiveView":0,"follower":14112,"time":1630380575559},{"archiveView":0,"follower":14129,"time":1630392981363},{"archiveView":0,"follower":14144,"time":1630408862045},{"archiveView":0,"follower":14164,"time":1630414993456},{"archiveView":0,"follower":14179,"time":1630420888096},{"archiveView":0,"follower":14194,"time":1630446857407},{"archiveView":0,"follower":14210,"time":1630468046074},{"archiveView":0,"follower":14228,"time":1630478612174},{"archiveView":0,"follower":14243,"time":1630481638186},{"archiveView":0,"follower":14260,"time":1630492894866},{"archiveView":0,"follower":14276,"time":1630503957637},{"archiveView":0,"follower":14294,"time":1630517691842},{"archiveView":0,"follower":14314,"time":1630544836574},{"archiveView":0,"follower":14332,"time":1630567047085},{"archiveView":0,"follower":14347,"time":1630585535400},{"archiveView":0,"follower":14362,"time":1630592061943},{"archiveView":0,"follower":14377,"time":1630599275861},{"archiveView":0,"follower":14393,"time":1630618143421},{"archiveView":0,"follower":14410,"time":1630637872492},{"archiveView":0,"follower":14425,"time":1630651896337},{"archiveView":0,"follower":14440,"time":1630669608837},{"archiveView":0,"follower":14455,"time":1630676381988},{"archiveView":0,"follower":14472,"time":1630681362124},{"archiveView":0,"follower":14487,"time":1630688116821},{"archiveView":0,"follower":14508,"time":1630693138706},{"archiveView":0,"follower":14528,"time":1630700171230},{"archiveView":0,"follower":14548,"time":1630731087253},{"archiveView":0,"follower":14565,"time":1630738180174},{"archiveView":0,"follower":14580,"time":1630745802521},{"archiveView":0,"follower":14595,"time":1630757250519},{"archiveView":0,"follower":14610,"time":1630762692953},{"archiveView":0,"follower":14625,"time":1630766670284},{"archiveView":0,"follower":14643,"time":1630772032761},{"archiveView":0,"follower":14667,"time":1630781519544},{"archiveView":0,"follower":14690,"time":1630785160828},{"archiveView":0,"follower":14705,"time":1630810932495},{"archiveView":0,"follower":14720,"time":1630823274023},{"archiveView":0,"follower":14735,"time":1630833879516},{"archiveView":0,"follower":14751,"time":1630848817465},{"archiveView":0,"follower":14767,"time":1630896139062},{"archiveView":0,"follower":14782,"time":1630919181107},{"archiveView":0,"follower":14799,"time":1630937194837},{"archiveView":0,"follower":14814,"time":1630943092386},{"archiveView":0,"follower":14829,"time":1630949521257},{"archiveView":0,"follower":14844,"time":1631001456380},{"archiveView":0,"follower":14860,"time":1631067897312},{"archiveView":0,"follower":14875,"time":1631100602640},{"archiveView":0,"follower":14891,"time":1631105955192},{"archiveView":0,"follower":14906,"time":1631115800059},{"archiveView":0,"follower":14922,"time":1631137183570},{"archiveView":0,"follower":14938,"time":1631161890295},{"archiveView":0,"follower":14953,"time":1631183530638},{"archiveView":0,"follower":14968,"time":1631199891841},{"archiveView":0,"follower":14983,"time":1631240772729},{"archiveView":0,"follower":14998,"time":1631267380585},{"archiveView":0,"follower":15013,"time":1631276738074},{"archiveView":0,"follower":15034,"time":1631279487847},{"archiveView":0,"follower":15054,"time":1631283211090},{"archiveView":0,"follower":15071,"time":1631290412903},{"archiveView":0,"follower":15087,"time":1631303876831},{"archiveView":0,"follower":15103,"time":1631346611541},{"archiveView":0,"follower":15120,"time":1631366715584},{"archiveView":0,"follower":15138,"time":1631385050551},{"archiveView":0,"follower":15155,"time":1631395715693},{"archiveView":0,"follower":15171,"time":1631451763985},{"archiveView":0,"follower":15188,"time":1631464016666},{"archiveView":0,"follower":15205,"time":1631491576605},{"archiveView":0,"follower":15222,"time":1631519176456},{"archiveView":0,"follower":15238,"time":1631536082420},{"archiveView":0,"follower":15256,"time":1631582176588},{"archiveView":0,"follower":15272,"time":1631611474958},{"archiveView":0,"follower":15294,"time":1631625653679},{"archiveView":0,"follower":15310,"time":1631626790923},{"archiveView":0,"follower":15326,"time":1631631428155},{"archiveView":0,"follower":15343,"time":1631672985374},{"archiveView":0,"follower":15359,"time":1631710529371},{"archiveView":0,"follower":15375,"time":1631729074383},{"archiveView":0,"follower":15391,"time":1631787928251},{"archiveView":0,"follower":15409,"time":1631805362025},{"archiveView":0,"follower":15425,"time":1631881038822},{"archiveView":0,"follower":15449,"time":1631944050472},{"archiveView":0,"follower":15467,"time":1631951934756},{"archiveView":0,"follower":15490,"time":1631957195015},{"archiveView":0,"follower":15508,"time":1631963872629},{"archiveView":0,"follower":15536,"time":1631969968180},{"archiveView":0,"follower":15554,"time":1631971559371},{"archiveView":0,"follower":15575,"time":1631974000373},{"archiveView":0,"follower":15595,"time":1631977513440},{"archiveView":0,"follower":15611,"time":1631981439503},{"archiveView":0,"follower":15628,"time":1632016723887},{"archiveView":0,"follower":15644,"time":1632037368316},{"archiveView":0,"follower":15660,"time":1632051582563},{"archiveView":0,"follower":15695,"time":1632054252710},{"archiveView":0,"follower":15712,"time":1632057534034},{"archiveView":0,"follower":15728,"time":1632061894617},{"archiveView":0,"follower":15746,"time":1632064953141},{"archiveView":0,"follower":15765,"time":1632068272897},{"archiveView":0,"follower":15782,"time":1632070822370},{"archiveView":0,"follower":15800,"time":1632078598182},{"archiveView":0,"follower":15817,"time":1632106355961},{"archiveView":0,"follower":15833,"time":1632128237985},{"archiveView":0,"follower":15849,"time":1632146447076},{"archiveView":0,"follower":15865,"time":1632157985243},{"archiveView":0,"follower":15881,"time":1632180842847},{"archiveView":0,"follower":15897,"time":1632197868362},{"archiveView":0,"follower":15914,"time":1632228869265},{"archiveView":0,"follower":15945,"time":1632234938320},{"archiveView":0,"follower":15962,"time":1632252322054},{"archiveView":0,"follower":15978,"time":1632293683457},{"archiveView":0,"follower":15995,"time":1632322877507},{"archiveView":0,"follower":16011,"time":1632347180969},{"archiveView":0,"follower":16028,"time":1632413460238},{"archiveView":0,"follower":16045,"time":1632496103787},{"archiveView":0,"follower":16068,"time":1632552184866},{"archiveView":0,"follower":16091,"time":1632566616622},{"archiveView":0,"follower":16112,"time":1632574023066},{"archiveView":0,"follower":16130,"time":1632580796920},{"archiveView":0,"follower":16149,"time":1632583541831},{"archiveView":0,"follower":16166,"time":1632597329325},{"archiveView":0,"follower":16187,"time":1632621869909},{"archiveView":0,"follower":16204,"time":1632628531988},{"archiveView":0,"follower":16221,"time":1632633588027},{"archiveView":0,"follower":16240,"time":1632656485103},{"archiveView":0,"follower":16260,"time":1632673321198},{"archiveView":0,"follower":16277,"time":1632682734092},{"archiveView":0,"follower":16365,"time":1632715562303},{"archiveView":0,"follower":16598,"time":1632717598274},{"archiveView":0,"follower":16765,"time":1632719862827},{"archiveView":0,"follower":16859,"time":1632721991960},{"archiveView":0,"follower":16933,"time":1632726006648},{"archiveView":0,"follower":16981,"time":1632728885187},{"archiveView":0,"follower":17016,"time":1632731231603},{"archiveView":0,"follower":17056,"time":1632733350827},{"archiveView":0,"follower":17117,"time":1632735571552},{"archiveView":0,"follower":17161,"time":1632737460110},{"archiveView":0,"follower":17188,"time":1632739246595},{"archiveView":0,"follower":17225,"time":1632741075375},{"archiveView":0,"follower":17253,"time":1632742586461},{"archiveView":0,"follower":17348,"time":1632744146868},{"archiveView":0,"follower":17443,"time":1632745586279},{"archiveView":0,"follower":17562,"time":1632747279545},{"archiveView":0,"follower":17678,"time":1632749029938},{"archiveView":0,"follower":17823,"time":1632750887223},{"archiveView":0,"follower":17972,"time":1632752750088},{"archiveView":0,"follower":18103,"time":1632754376866},{"archiveView":0,"follower":18214,"time":1632755854843},{"archiveView":0,"follower":18315,"time":1632757394288},{"archiveView":0,"follower":18347,"time":1632759043516},{"archiveView":0,"follower":18372,"time":1632760871073},{"archiveView":0,"follower":18397,"time":1632762799412},{"archiveView":0,"follower":18428,"time":1632764816912},{"archiveView":0,"follower":18455,"time":1632769670577},{"archiveView":0,"follower":18491,"time":1632781325116},{"archiveView":0,"follower":18514,"time":1632785340493},{"archiveView":0,"follower":18550,"time":1632789506743},{"archiveView":0,"follower":18571,"time":1632792510453},{"archiveView":0,"follower":18591,"time":1632795431964},{"archiveView":0,"follower":18614,"time":1632798255482},{"archiveView":0,"follower":18643,"time":1632800828103},{"archiveView":0,"follower":18664,"time":1632807527783},{"archiveView":0,"follower":18687,"time":1632821080961},{"archiveView":0,"follower":18707,"time":1632837611809},{"archiveView":0,"follower":18726,"time":1632850716526},{"archiveView":0,"follower":18750,"time":1632916649502},{"archiveView":0,"follower":18770,"time":1632965765430},{"archiveView":0,"follower":18790,"time":1632990366502},{"archiveView":0,"follower":18810,"time":1633003874745},{"archiveView":0,"follower":18832,"time":1633020164036},{"archiveView":0,"follower":18852,"time":1633028558362},{"archiveView":0,"follower":18873,"time":1633054237736},{"archiveView":0,"follower":18892,"time":1633074150691},{"archiveView":0,"follower":18912,"time":1633103849403},{"archiveView":0,"follower":18932,"time":1633137824757},{"archiveView":0,"follower":18953,"time":1633158683607},{"archiveView":0,"follower":18973,"time":1633174570117},{"archiveView":0,"follower":18992,"time":1633189259745},{"archiveView":0,"follower":19011,"time":1633219704900},{"archiveView":0,"follower":19032,"time":1633240120753},{"archiveView":0,"follower":19054,"time":1633257276930},{"archiveView":0,"follower":19079,"time":1633283107892},{"archiveView":0,"follower":19102,"time":1633319337693},{"archiveView":0,"follower":19122,"time":1633346271791},{"archiveView":0,"follower":19142,"time":1633407940421},{"archiveView":0,"follower":19162,"time":1633447929732},{"archiveView":0,"follower":19185,"time":1633515440881},{"archiveView":0,"follower":19212,"time":1633526548992},{"archiveView":0,"follower":19233,"time":1633533966479},{"archiveView":0,"follower":19256,"time":1633544136742},{"archiveView":0,"follower":19276,"time":1633583594176},{"archiveView":0,"follower":19297,"time":1633597176368},{"archiveView":0,"follower":19318,"time":1633626611730},{"archiveView":0,"follower":19342,"time":1633682870215},{"archiveView":0,"follower":19365,"time":1633716613041},{"archiveView":0,"follower":19385,"time":1633791584806},{"archiveView":0,"follower":19405,"time":1633879681434},{"archiveView":0,"follower":19425,"time":1633934897826},{"archiveView":0,"follower":19445,"time":1633957664214},{"archiveView":0,"follower":19467,"time":1634043342723},{"archiveView":0,"follower":19489,"time":1634139372256},{"archiveView":0,"follower":19510,"time":1634200289060},{"archiveView":0,"follower":19530,"time":1634261465719},{"archiveView":0,"follower":19553,"time":1634301269970},{"archiveView":0,"follower":19574,"time":1634307942598},{"archiveView":0,"follower":19596,"time":1634325319653},{"archiveView":0,"follower":19616,"time":1634371640320},{"archiveView":0,"follower":19636,"time":1634396057946},{"archiveView":0,"follower":19656,"time":1634434690040},{"archiveView":0,"follower":19676,"time":1634464345364},{"archiveView":0,"follower":19699,"time":1634491797879},{"archiveView":0,"follower":19720,"time":1634566868149},{"archiveView":0,"follower":19742,"time":1634613042966},{"archiveView":0,"follower":19762,"time":1634659163475},{"archiveView":0,"follower":19784,"time":1634728215381},{"archiveView":0,"follower":19805,"time":1634743929471},{"archiveView":0,"follower":19825,"time":1634799941819},{"archiveView":0,"follower":19845,"time":1634867398745},{"archiveView":0,"follower":19866,"time":1634924511023},{"archiveView":0,"follower":19887,"time":1634988249630},{"archiveView":0,"follower":19899,"time":1635106366517},{"archiveView":0,"follower":19918,"time":1635223743785},{"archiveView":0,"follower":19938,"time":1635276687976},{"archiveView":0,"follower":19958,"time":1635348611968},{"archiveView":0,"follower":19976,"time":1635466797640},{"archiveView":0,"follower":20103,"time":1635807576575},{"archiveView":0,"follower":20116,"time":1635924122916},{"archiveView":0,"follower":20137,"time":1635941291396},{"archiveView":0,"follower":20159,"time":1636034075808},{"archiveView":0,"follower":20185,"time":1636110906000},{"archiveView":0,"follower":20208,"time":1636121323374},{"archiveView":0,"follower":20231,"time":1636136995350},{"archiveView":0,"follower":20253,"time":1636171946869},{"archiveView":0,"follower":20275,"time":1636214768223},{"archiveView":0,"follower":20344,"time":1636219592911},{"archiveView":0,"follower":20647,"time":1636221870338},{"archiveView":0,"follower":20638,"time":1636338789914},{"archiveView":0,"follower":20662,"time":1636455862059},{"archiveView":0,"follower":20686,"time":1636508234964},{"archiveView":0,"follower":20707,"time":1636525015912},{"archiveView":0,"follower":20728,"time":1636564563189},{"archiveView":0,"follower":20750,"time":1636637636044},{"archiveView":0,"follower":20773,"time":1636708772031},{"archiveView":0,"follower":20796,"time":1636720050229},{"archiveView":0,"follower":20820,"time":1636725204242},{"archiveView":0,"follower":20842,"time":1636761659171},{"archiveView":0,"follower":20864,"time":1636787297110},{"archiveView":0,"follower":20895,"time":1636807019104},{"archiveView":0,"follower":20935,"time":1636813051235},{"archiveView":0,"follower":20959,"time":1636819892709},{"archiveView":0,"follower":20982,"time":1636838689001},{"archiveView":0,"follower":21008,"time":1636868387286},{"archiveView":0,"follower":21034,"time":1636885515428},{"archiveView":0,"follower":21058,"time":1636897416273},{"archiveView":0,"follower":21083,"time":1636904867707},{"archiveView":0,"follower":21114,"time":1636907423747},{"archiveView":0,"follower":21138,"time":1636914231997},{"archiveView":0,"follower":21165,"time":1636950270365},{"archiveView":0,"follower":21188,"time":1636969276946},{"archiveView":0,"follower":21210,"time":1636988366770},{"archiveView":0,"follower":21232,"time":1637032927555},{"archiveView":0,"follower":21257,"time":1637077665112},{"archiveView":0,"follower":21282,"time":1637082011205},{"archiveView":0,"follower":21304,"time":1637133902053},{"archiveView":0,"follower":21326,"time":1637240589702},{"archiveView":0,"follower":21353,"time":1637303838515},{"archiveView":0,"follower":21378,"time":1637342755737},{"archiveView":0,"follower":21405,"time":1637384424210},{"archiveView":0,"follower":21430,"time":1637414275130},{"archiveView":0,"follower":21452,"time":1637417750303},{"archiveView":0,"follower":21478,"time":1637421963569},{"archiveView":0,"follower":21501,"time":1637424109895},{"archiveView":0,"follower":21524,"time":1637428158219},{"archiveView":0,"follower":21557,"time":1637440400521},{"archiveView":0,"follower":21583,"time":1637453059710},{"archiveView":0,"follower":21608,"time":1637458347827},{"archiveView":0,"follower":21636,"time":1637462453820},{"archiveView":0,"follower":21669,"time":1637468258946},{"archiveView":0,"follower":21691,"time":1637478511301},{"archiveView":0,"follower":21714,"time":1637493502616},{"archiveView":0,"follower":21739,"time":1637509015838},{"archiveView":0,"follower":21762,"time":1637514727032},{"archiveView":0,"follower":21785,"time":1637545693631},{"archiveView":0,"follower":21810,"time":1637562295240},{"archiveView":0,"follower":21832,"time":1637589076115},{"archiveView":0,"follower":23636,"time":1638705540942},{"archiveView":0,"follower":23661,"time":1638716094744},{"archiveView":0,"follower":23686,"time":1638724676132},{"archiveView":0,"follower":23710,"time":1638745460371},{"archiveView":0,"follower":23767,"time":1638791692359},{"archiveView":0,"follower":23819,"time":1638796119852},{"archiveView":0,"follower":23903,"time":1638798029125},{"archiveView":0,"follower":23934,"time":1638799881680},{"archiveView":0,"follower":23961,"time":1638801625745},{"archiveView":0,"follower":23994,"time":1638804928081},{"archiveView":0,"follower":24026,"time":1638810267869},{"archiveView":0,"follower":24053,"time":1638844565484},{"archiveView":0,"follower":24079,"time":1638881916083},{"archiveView":0,"follower":24106,"time":1638890552985},{"archiveView":0,"follower":24131,"time":1638927889067},{"archiveView":0,"follower":24156,"time":1638970820824},{"archiveView":0,"follower":24186,"time":1638975735139},{"archiveView":0,"follower":24212,"time":1639030574268},{"archiveView":0,"follower":24241,"time":1639053811556},{"archiveView":0,"follower":24268,"time":1639062893255},{"archiveView":0,"follower":24293,"time":1639070565205},{"archiveView":0,"follower":24332,"time":1639134290414},{"archiveView":0,"follower":24360,"time":1639137242010},{"archiveView":0,"follower":24391,"time":1639150479908},{"archiveView":0,"follower":24424,"time":1639153699071},{"archiveView":0,"follower":24459,"time":1639160123497},{"archiveView":0,"follower":24487,"time":1639184511518},{"archiveView":0,"follower":24518,"time":1639194542666},{"archiveView":0,"follower":24548,"time":1639211816099},{"archiveView":0,"follower":24573,"time":1639233574548},{"archiveView":0,"follower":24606,"time":1639253805748},{"archiveView":0,"follower":24632,"time":1639306573147},{"archiveView":0,"follower":24658,"time":1639331375688},{"archiveView":0,"follower":24684,"time":1639365331181},{"archiveView":0,"follower":24711,"time":1639387592215},{"archiveView":0,"follower":24738,"time":1639408603481},{"archiveView":0,"follower":24763,"time":1639453183480},{"archiveView":0,"follower":24788,"time":1639485200802},{"archiveView":0,"follower":24816,"time":1639498930641},{"archiveView":0,"follower":24841,"time":1639614046821},{"archiveView":0,"follower":24867,"time":1639662787023},{"archiveView":0,"follower":24892,"time":1639698688671},{"archiveView":0,"follower":24917,"time":1639740979473},{"archiveView":0,"follower":27004,"time":1639741813038},{"archiveView":0,"follower":26847,"time":1639742584839},{"archiveView":0,"follower":26875,"time":1639817874729},{"archiveView":0,"follower":26928,"time":1639823623751},{"archiveView":0,"follower":26957,"time":1639830975119},{"archiveView":0,"follower":26984,"time":1639835166725},{"archiveView":0,"follower":27014,"time":1639847454701},{"archiveView":0,"follower":27042,"time":1639872760447},{"archiveView":0,"follower":27075,"time":1639889314558},{"archiveView":0,"follower":27104,"time":1639898690929},{"archiveView":0,"follower":27133,"time":1639906319843},{"archiveView":0,"follower":27163,"time":1639930244683},{"archiveView":0,"follower":27191,"time":1639976960694},{"archiveView":0,"follower":27219,"time":1640022863905},{"archiveView":0,"follower":27247,"time":1640071672041},{"archiveView":0,"follower":27275,"time":1640098732905},{"archiveView":0,"follower":27303,"time":1640191876554},{"archiveView":0,"follower":27331,"time":1640281921022},{"archiveView":0,"follower":27371,"time":1640307951422},{"archiveView":0,"follower":27399,"time":1640329207064},{"archiveView":0,"follower":27427,"time":1640336458293},{"archiveView":0,"follower":27456,"time":1640352139569},{"archiveView":0,"follower":27485,"time":1640401014174},{"archiveView":0,"follower":27515,"time":1640456542768},{"archiveView":0,"follower":27545,"time":1640507230584},{"archiveView":0,"follower":27582,"time":1640518036479},{"archiveView":0,"follower":27633,"time":1640518709276},{"archiveView":0,"follower":27721,"time":1640519333671},{"archiveView":0,"follower":27749,"time":1640521145527},{"archiveView":0,"follower":27780,"time":1640524049615},{"archiveView":0,"follower":27814,"time":1640526873426},{"archiveView":0,"follower":27844,"time":1640530018373},{"archiveView":0,"follower":27946,"time":1640531247570},{"archiveView":0,"follower":27975,"time":1640541101247},{"archiveView":0,"follower":28004,"time":1640577955237},{"archiveView":0,"follower":28033,"time":1640604001924},{"archiveView":0,"follower":28063,"time":1640625344653},{"archiveView":0,"follower":28092,"time":1640693274787},{"archiveView":0,"follower":28123,"time":1640785145551},{"archiveView":0,"follower":28134,"time":1640905113338},{"archiveView":0,"follower":28163,"time":1640957121898},{"archiveView":0,"follower":28192,"time":1640965888427},{"archiveView":0,"follower":28221,"time":1641015382574},{"archiveView":0,"follower":28252,"time":1641054341270},{"archiveView":0,"follower":28281,"time":1641101377727},{"archiveView":0,"follower":28314,"time":1641140997890},{"archiveView":0,"follower":28356,"time":1641185250595},{"archiveView":0,"follower":28385,"time":1641215731555},{"archiveView":0,"follower":28416,"time":1641299289988},{"archiveView":0,"follower":28445,"time":1641376091517},{"archiveView":0,"follower":28475,"time":1641450100105},{"archiveView":0,"follower":28484,"time":1641566213276},{"archiveView":0,"follower":28514,"time":1641656545835},{"archiveView":0,"follower":28544,"time":1641701755650},{"archiveView":0,"follower":28560,"time":1641817398161},{"archiveView":0,"follower":28562,"time":1641933923630},{"archiveView":0,"follower":28593,"time":1642044937863},{"archiveView":0,"follower":28609,"time":1642162168317},{"archiveView":0,"follower":28641,"time":1642239072229},{"archiveView":0,"follower":28677,"time":1642304482624},{"archiveView":0,"follower":28687,"time":1642420981645},{"archiveView":0,"follower":28706,"time":1642537294846},{"archiveView":0,"follower":28736,"time":1642587965048},{"archiveView":0,"follower":28765,"time":1642648857804},{"archiveView":0,"follower":28793,"time":1642765549217},{"archiveView":0,"follower":28822,"time":1642769206689},{"archiveView":0,"follower":28941,"time":1642770655345},{"archiveView":0,"follower":28974,"time":1642773119015},{"archiveView":0,"follower":29004,"time":1642831931196},{"archiveView":0,"follower":29052,"time":1642858421813},{"archiveView":0,"follower":29083,"time":1642867181968},{"archiveView":0,"follower":29113,"time":1642950068604},{"archiveView":0,"follower":29143,"time":1643066193406},{"archiveView":0,"follower":29171,"time":1643181421637},{"archiveView":0,"follower":29207,"time":1643228620580},{"archiveView":0,"follower":29227,"time":1643344951302},{"archiveView":0,"follower":29263,"time":1643365648416},{"archiveView":0,"follower":29447,"time":1643370432931},{"archiveView":0,"follower":29993,"time":1643373181787},{"archiveView":0,"follower":30167,"time":1643375378612},{"archiveView":0,"follower":30260,"time":1643376865233},{"archiveView":0,"follower":30321,"time":1643378213648},{"archiveView":0,"follower":30397,"time":1643379731225},{"archiveView":0,"follower":30443,"time":1643382014685},{"archiveView":0,"follower":30503,"time":1643387691522},{"archiveView":0,"follower":30539,"time":1643388919375},{"archiveView":0,"follower":30570,"time":1643394991187},{"archiveView":0,"follower":30608,"time":1643419410923},{"archiveView":0,"follower":30640,"time":1643423416634},{"archiveView":0,"follower":30674,"time":1643428633084},{"archiveView":0,"follower":30709,"time":1643435675285},{"archiveView":0,"follower":30742,"time":1643448002696},{"archiveView":0,"follower":30892,"time":1643459236687},{"archiveView":0,"follower":30957,"time":1643460422516},{"archiveView":0,"follower":30988,"time":1643466968246},{"archiveView":0,"follower":31019,"time":1643486277099},{"archiveView":0,"follower":31058,"time":1643509180036},{"archiveView":0,"follower":31092,"time":1643521084937},{"archiveView":0,"follower":31126,"time":1643533173164},{"archiveView":0,"follower":31173,"time":1643553437282},{"archiveView":0,"follower":31238,"time":1643604397144},{"archiveView":0,"follower":31964,"time":1643712171059},{"archiveView":0,"follower":32286,"time":1643921099805},{"archiveView":0,"follower":32291,"time":1644036690493},{"archiveView":0,"follower":32317,"time":1644152144607},{"archiveView":0,"follower":32351,"time":1644224060930},{"archiveView":0,"follower":32371,"time":1644339957783},{"archiveView":0,"follower":32390,"time":1644455263973},{"archiveView":0,"follower":32357,"time":1644528555070},{"archiveView":0,"follower":32324,"time":1644577428392},{"archiveView":0,"follower":32291,"time":1644659960069},{"archiveView":0,"follower":32325,"time":1644668810702},{"archiveView":0,"follower":32359,"time":1644728535067},{"archiveView":0,"follower":32392,"time":1644813777094},{"archiveView":0,"follower":32425,"time":1644923385632},{"archiveView":0,"follower":32473,"time":1645001308228},{"archiveView":0,"follower":32481,"time":1645116738631},{"archiveView":0,"follower":32525,"time":1645206669397},{"archiveView":0,"follower":32547,"time":1645321994319},{"archiveView":0,"follower":32561,"time":1645437516284},{"archiveView":0,"follower":32353,"time":1645504204378},{"archiveView":0,"follower":32287,"time":1645504976136},{"archiveView":0,"follower":32236,"time":1645505747966},{"archiveView":0,"follower":32167,"time":1645506423261},{"archiveView":0,"follower":32119,"time":1645507079870},{"archiveView":0,"follower":32052,"time":1645507751059},{"archiveView":0,"follower":32003,"time":1645508362451},{"archiveView":0,"follower":31967,"time":1645509028295},{"archiveView":0,"follower":31996,"time":1645624494813},{"archiveView":0,"follower":32012,"time":1645740095243},{"archiveView":0,"follower":32036,"time":1645855348421},{"archiveView":0,"follower":32069,"time":1645944787066},{"archiveView":0,"follower":32130,"time":1645977850916},{"archiveView":0,"follower":32124,"time":1646094254177},{"archiveView":0,"follower":32150,"time":1646210052146},{"archiveView":0,"follower":32157,"time":1646325412234},{"archiveView":0,"follower":32180,"time":1646440840858},{"archiveView":0,"follower":32213,"time":1646508467864},{"archiveView":0,"follower":32249,"time":1646534298630},{"archiveView":0,"follower":32283,"time":1646549078692},{"archiveView":0,"follower":32314,"time":1646664822850},{"archiveView":0,"follower":32321,"time":1646781253046},{"archiveView":0,"follower":32320,"time":1646896811311},{"archiveView":0,"follower":32334,"time":1647012047663},{"archiveView":0,"follower":32436,"time":1647015219899},{"archiveView":0,"follower":32469,"time":1647107607206},{"archiveView":0,"follower":32503,"time":1647119218608},{"archiveView":0,"follower":32538,"time":1647131922377},{"archiveView":0,"follower":32591,"time":1647178665256},{"archiveView":0,"follower":32569,"time":1647294103284},{"archiveView":0,"follower":32579,"time":1647409837234},{"archiveView":0,"follower":32613,"time":1647518861065},{"archiveView":0,"follower":32646,"time":1647530481671},{"archiveView":0,"follower":32679,"time":1647536642633},{"archiveView":0,"follower":32712,"time":1647632357611},{"archiveView":0,"follower":32767,"time":1647694998908},{"archiveView":0,"follower":32830,"time":1647709636599},{"archiveView":0,"follower":32865,"time":1647770521057},{"archiveView":0,"follower":32899,"time":1647780992020},{"archiveView":0,"follower":32969,"time":1647789344741},{"archiveView":0,"follower":33019,"time":1647789803997},{"archiveView":0,"follower":33058,"time":1647876753290},{"archiveView":0,"follower":33092,"time":1647885634460},{"archiveView":0,"follower":33126,"time":1647921227246},{"archiveView":0,"follower":33166,"time":1647970950338},{"archiveView":0,"follower":33253,"time":1648026979197},{"archiveView":0,"follower":33288,"time":1648141380817},{"archiveView":0,"follower":33327,"time":1648227620920},{"archiveView":0,"follower":33369,"time":1648230837478},{"archiveView":0,"follower":33413,"time":1648231749224},{"archiveView":0,"follower":33460,"time":1648326424666},{"archiveView":0,"follower":33497,"time":1648392697611},{"archiveView":0,"follower":33487,"time":1648509096267},{"archiveView":0,"follower":33483,"time":1648625214180},{"archiveView":0,"follower":33461,"time":1648741095975},{"archiveView":0,"follower":36246,"time":1648743455767},{"archiveView":0,"follower":36146,"time":1648744795037},{"archiveView":0,"follower":36095,"time":1648830612331},{"archiveView":0,"follower":36059,"time":1648913868017},{"archiveView":0,"follower":36045,"time":1649031559381},{"archiveView":0,"follower":36054,"time":1649147910234},{"archiveView":0,"follower":36069,"time":1649263339437},{"archiveView":0,"follower":36143,"time":1649355020586},{"archiveView":0,"follower":36204,"time":1649426393012},{"archiveView":0,"follower":36189,"time":1649542877712},{"archiveView":0,"follower":38335,"time":1649595634858},{"archiveView":0,"follower":38295,"time":1649596614358},{"archiveView":0,"follower":38248,"time":1649601552151},{"archiveView":0,"follower":38199,"time":1649607425231},{"archiveView":0,"follower":38157,"time":1649639940147},{"archiveView":0,"follower":38116,"time":1649663114638},{"archiveView":0,"follower":38205,"time":1649683006185},{"archiveView":0,"follower":38330,"time":1649694495594},{"archiveView":0,"follower":38294,"time":1649695786482},{"archiveView":0,"follower":38256,"time":1649725583770},{"archiveView":0,"follower":38216,"time":1649750114820},{"archiveView":0,"follower":38179,"time":1649814659339},{"archiveView":0,"follower":38142,"time":1649860320769},{"archiveView":0,"follower":38106,"time":1649906261031},{"archiveView":0,"follower":38075,"time":1650022647262},{"archiveView":0,"follower":38087,"time":1650138432080},{"archiveView":0,"follower":38056,"time":1650254933306},{"archiveView":0,"follower":38032,"time":1650370404130},{"archiveView":0,"follower":37996,"time":1650449580198},{"archiveView":0,"follower":38010,"time":1650565103684},{"archiveView":0,"follower":37991,"time":1650681255444},{"archiveView":0,"follower":37987,"time":1650796632178},{"archiveView":0,"follower":38028,"time":1650897425514},{"archiveView":0,"follower":38029,"time":1651013422546},{"archiveView":0,"follower":38019,"time":1651154966787},{"archiveView":0,"follower":38001,"time":1651272163072},{"archiveView":0,"follower":38036,"time":1651387707662},{"archiveView":0,"follower":38550,"time":1651408541615},{"archiveView":0,"follower":38642,"time":1651465995074},{"archiveView":0,"follower":38619,"time":1651581888560},{"archiveView":0,"follower":38660,"time":1651689551235},{"archiveView":0,"follower":38693,"time":1651805389814},{"archiveView":0,"follower":38731,"time":1651811801934},{"archiveView":0,"follower":38775,"time":1651813870393},{"archiveView":0,"follower":38811,"time":1651816681129},{"archiveView":0,"follower":38850,"time":1651823921446},{"archiveView":0,"follower":38889,"time":1651830108634},{"archiveView":0,"follower":38931,"time":1651837842201},{"archiveView":0,"follower":38967,"time":1651850424067},{"archiveView":0,"follower":39004,"time":1651889431971},{"archiveView":0,"follower":39048,"time":1651952181562},{"archiveView":0,"follower":39094,"time":1652017392057},{"archiveView":0,"follower":39081,"time":1652133363922},{"archiveView":0,"follower":39097,"time":1652248796725},{"archiveView":0,"follower":39118,"time":1652363997232},{"archiveView":0,"follower":39157,"time":1652447069110},{"archiveView":0,"follower":39313,"time":1652458590172},{"archiveView":0,"follower":39277,"time":1652460351398},{"archiveView":0,"follower":39313,"time":1652544020128},{"archiveView":0,"follower":39349,"time":1652558553361},{"archiveView":0,"follower":39385,"time":1652620703985},{"archiveView":0,"follower":39421,"time":1652714142945},{"archiveView":0,"follower":39511,"time":1652715371194},{"archiveView":0,"follower":39503,"time":1652830790373},{"archiveView":0,"follower":39539,"time":1652881104697},{"archiveView":0,"follower":39609,"time":1652890293608},{"archiveView":0,"follower":39642,"time":1653010866748},{"archiveView":0,"follower":39710,"time":1653052489989},{"archiveView":0,"follower":39755,"time":1653137623582},{"archiveView":0,"follower":39792,"time":1653234218063},{"archiveView":0,"follower":39848,"time":1653320939863},{"archiveView":0,"follower":39822,"time":1653436196127},{"archiveView":0,"follower":39807,"time":1653551420684},{"archiveView":0,"follower":39937,"time":1653569997902},{"archiveView":0,"follower":40053,"time":1653571192030},{"archiveView":0,"follower":40014,"time":1653573314173},{"archiveView":0,"follower":40247,"time":1653574594940},{"archiveView":0,"follower":40206,"time":1653576086672},{"archiveView":0,"follower":40166,"time":1653579108266},{"archiveView":0,"follower":40130,"time":1653611296758},{"archiveView":0,"follower":41050,"time":1653654171738},{"archiveView":0,"follower":41311,"time":1653654471792},{"archiveView":0,"follower":41275,"time":1653661713931},{"archiveView":0,"follower":41239,"time":1653670024829},{"archiveView":0,"follower":41346,"time":1653753704209},{"archiveView":0,"follower":41309,"time":1653756198274},{"archiveView":0,"follower":41243,"time":1653757784105},{"archiveView":0,"follower":41207,"time":1653815382198},{"archiveView":0,"follower":41302,"time":1653840621759},{"archiveView":0,"follower":41265,"time":1653844376074},{"archiveView":0,"follower":41263,"time":1653959938243},{"archiveView":0,"follower":41234,"time":1654075263780},{"archiveView":0,"follower":41486,"time":1654088352327},{"archiveView":0,"follower":41637,"time":1654088656589},{"archiveView":0,"follower":41567,"time":1654088944673},{"archiveView":0,"follower":41528,"time":1654089245028},{"archiveView":0,"follower":41482,"time":1654089846396},{"archiveView":0,"follower":41443,"time":1654091361053},{"archiveView":0,"follower":41305,"time":1654092005049},{"archiveView":0,"follower":41269,"time":1654109959214},{"archiveView":0,"follower":41233,"time":1654166127893},{"archiveView":0,"follower":41197,"time":1654253383104},{"archiveView":0,"follower":41187,"time":1654368618407},{"archiveView":0,"follower":41206,"time":1654483971052},{"archiveView":0,"follower":41198,"time":1654599257438},{"archiveView":0,"follower":41295,"time":1654610650761},{"archiveView":0,"follower":41271,"time":1654726459061},{"archiveView":0,"follower":41246,"time":1654842002918},{"archiveView":0,"follower":41266,"time":1654957429000},{"archiveView":0,"follower":41305,"time":1654995316319},{"archiveView":0,"follower":41316,"time":1655110570954},{"archiveView":0,"follower":41346,"time":1655225852594},{"archiveView":0,"follower":41371,"time":1655341371423},{"archiveView":0,"follower":41379,"time":1655456784652},{"archiveView":0,"follower":41483,"time":1655485710931},{"archiveView":0,"follower":41531,"time":1655487636476},{"archiveView":0,"follower":41494,"time":1655521934604},{"archiveView":0,"follower":41516,"time":1655637489468},{"archiveView":0,"follower":41534,"time":1655752964564},{"archiveView":0,"follower":41508,"time":1655868518776},{"archiveView":0,"follower":41544,"time":1655917832798},{"archiveView":0,"follower":41521,"time":1656033116459},{"archiveView":0,"follower":41557,"time":1656094213229},{"archiveView":0,"follower":41563,"time":1656209639387},{"archiveView":0,"follower":41564,"time":1656325157789},{"archiveView":0,"follower":41787,"time":1656338327473},{"archiveView":0,"follower":41841,"time":1656338624987},{"archiveView":0,"follower":41927,"time":1656339251812},{"archiveView":0,"follower":41885,"time":1656339879932},{"archiveView":0,"follower":41846,"time":1656341738713},{"archiveView":0,"follower":41810,"time":1656345255824},{"archiveView":0,"follower":41774,"time":1656379235411},{"archiveView":0,"follower":41738,"time":1656422407677},{"archiveView":0,"follower":41822,"time":1656506880420},{"archiveView":0,"follower":41888,"time":1656507241682},{"archiveView":0,"follower":41851,"time":1656510262111},{"archiveView":0,"follower":41936,"time":1656603275110},{"archiveView":0,"follower":42012,"time":1656605422696},{"archiveView":0,"follower":41974,"time":1656606842910},{"archiveView":0,"follower":41938,"time":1656642471777},{"archiveView":0,"follower":41912,"time":1656758132849},{"archiveView":0,"follower":41960,"time":1656790417692},{"archiveView":0,"follower":41940,"time":1656906041036},{"archiveView":0,"follower":41976,"time":1656942280448},{"archiveView":0,"follower":42012,"time":1656967106526},{"archiveView":0,"follower":42049,"time":1657038116094},{"archiveView":0,"follower":42087,"time":1657042095128},{"archiveView":0,"follower":42123,"time":1657054353660},{"archiveView":0,"follower":42163,"time":1657071029959},{"archiveView":0,"follower":42199,"time":1657080769711},{"archiveView":0,"follower":42237,"time":1657093272700},{"archiveView":0,"follower":42275,"time":1657115408583},{"archiveView":0,"follower":42311,"time":1657133310983},{"archiveView":0,"follower":42347,"time":1657173746878},{"archiveView":0,"follower":42303,"time":1657197462815},{"archiveView":0,"follower":42266,"time":1657202899400},{"archiveView":0,"follower":42226,"time":1657211481841},{"archiveView":0,"follower":42187,"time":1657225365431},{"archiveView":0,"follower":42150,"time":1657229614657},{"archiveView":0,"follower":42112,"time":1657234184456},{"archiveView":0,"follower":42074,"time":1657241949337},{"archiveView":0,"follower":42038,"time":1657246817561},{"archiveView":0,"follower":42001,"time":1657257463277},{"archiveView":0,"follower":41962,"time":1657261933717},{"archiveView":0,"follower":41926,"time":1657268475815},{"archiveView":0,"follower":41890,"time":1657273560193},{"archiveView":0,"follower":42033,"time":1657282336041},{"archiveView":0,"follower":42126,"time":1657283304988},{"archiveView":0,"follower":42181,"time":1657283824620},{"archiveView":0,"follower":42251,"time":1657284336635},{"archiveView":0,"follower":42555,"time":1657285281921},{"archiveView":0,"follower":43802,"time":1657285804086},{"archiveView":0,"follower":43863,"time":1657287830249},{"archiveView":0,"follower":43955,"time":1657288842237},{"archiveView":0,"follower":43913,"time":1657290429530},{"archiveView":0,"follower":43877,"time":1657297212160},{"archiveView":0,"follower":43791,"time":1657300602856},{"archiveView":0,"follower":43745,"time":1657316135928},{"archiveView":0,"follower":43706,"time":1657319100017},{"archiveView":0,"follower":43670,"time":1657320658686},{"archiveView":0,"follower":43632,"time":1657322208001},{"archiveView":0,"follower":43584,"time":1657323768491},{"archiveView":0,"follower":43541,"time":1657325828495},{"archiveView":0,"follower":43503,"time":1657328671341},{"archiveView":0,"follower":43465,"time":1657330002272},{"archiveView":0,"follower":43418,"time":1657331982376},{"archiveView":0,"follower":43378,"time":1657333941051},{"archiveView":0,"follower":43328,"time":1657335581820},{"archiveView":0,"follower":43289,"time":1657364760742},{"archiveView":0,"follower":43253,"time":1657444520215},{"archiveView":0,"follower":43230,"time":1657560079341},{"archiveView":0,"follower":43270,"time":1657611904199},{"archiveView":0,"follower":43363,"time":1657617083864},{"archiveView":0,"follower":43382,"time":1657732824538},{"archiveView":0,"follower":43395,"time":1657848278916},{"archiveView":0,"follower":43383,"time":1657963843273},{"archiveView":0,"follower":43419,"time":1658026438194},{"archiveView":0,"follower":43433,"time":1658141933550},{"archiveView":0,"follower":43469,"time":1658245699984},{"archiveView":0,"follower":43479,"time":1658361302698},{"archiveView":0,"follower":43494,"time":1658476629863},{"archiveView":0,"follower":43510,"time":1658591934484},{"archiveView":0,"follower":43503,"time":1658707352595},{"archiveView":0,"follower":43539,"time":1658808902535},{"archiveView":0,"follower":43577,"time":1658891274277},{"archiveView":0,"follower":43613,"time":1658984005567},{"archiveView":0,"follower":43649,"time":1659028749284},{"archiveView":0,"follower":43682,"time":1659144079748},{"archiveView":0,"follower":43718,"time":1659188526372},{"archiveView":0,"follower":43767,"time":1659198896951},{"archiveView":0,"follower":43822,"time":1659200458575},{"archiveView":0,"follower":43942,"time":1659200787182},{"archiveView":0,"follower":44029,"time":1659201114672},{"archiveView":0,"follower":43990,"time":1659201777148},{"archiveView":0,"follower":43953,"time":1659235327013},{"archiveView":0,"follower":43946,"time":1659350752141},{"archiveView":0,"follower":43982,"time":1659414112353},{"archiveView":0,"follower":44018,"time":1659437794300},{"archiveView":0,"follower":44054,"time":1659481515915},{"archiveView":0,"follower":44090,"time":1659522016000},{"archiveView":0,"follower":44128,"time":1659543275205},{"archiveView":0,"follower":44164,"time":1659625390861},{"archiveView":0,"follower":44191,"time":1659740922379},{"archiveView":0,"follower":44227,"time":1659806366396},{"archiveView":0,"follower":44263,"time":1659845846222},{"archiveView":0,"follower":44300,"time":1659863924588},{"archiveView":0,"follower":44340,"time":1659874569348},{"archiveView":0,"follower":44400,"time":1659883594208},{"archiveView":0,"follower":44427,"time":1659999059605},{"archiveView":0,"follower":44456,"time":1660114614705},{"archiveView":0,"follower":44492,"time":1660215749031},{"archiveView":0,"follower":44499,"time":1660331165178},{"archiveView":0,"follower":44535,"time":1660413144797},{"archiveView":0,"follower":44538,"time":1660528537965},{"archiveView":0,"follower":44574,"time":1660620432071},{"archiveView":0,"follower":44611,"time":1660664641717},{"archiveView":0,"follower":44637,"time":1660780034193},{"archiveView":0,"follower":44673,"time":1660831058968},{"archiveView":0,"follower":44709,"time":1660905553451},{"archiveView":0,"follower":44745,"time":1660930712083},{"archiveView":0,"follower":44781,"time":1660998519966},{"archiveView":0,"follower":44817,"time":1661093878319},{"archiveView":0,"follower":44853,"time":1661122149860},{"archiveView":0,"follower":44889,"time":1661166344871},{"archiveView":0,"follower":44937,"time":1661172035660},{"archiveView":0,"follower":44973,"time":1661175935703},{"archiveView":0,"follower":45009,"time":1661229477378},{"archiveView":0,"follower":45045,"time":1661244867776},{"archiveView":0,"follower":45081,"time":1661266337135},{"archiveView":0,"follower":45117,"time":1661327996234},{"archiveView":0,"follower":45154,"time":1661345479991},{"archiveView":0,"follower":45221,"time":1661347279915},{"archiveView":0,"follower":45257,"time":1661412626802},{"archiveView":0,"follower":45294,"time":1661435954173},{"archiveView":0,"follower":45336,"time":1661509361512},{"archiveView":0,"follower":45375,"time":1661567880442},{"archiveView":0,"follower":45414,"time":1661676868509},{"archiveView":0,"follower":45450,"time":1661778500256},{"archiveView":0,"follower":45487,"time":1661852691099},{"archiveView":0,"follower":45523,"time":1661954881499},{"archiveView":0,"follower":45538,"time":1662071413381},{"archiveView":0,"follower":45546,"time":1662186850661},{"archiveView":0,"follower":45666,"time":1662220179938},{"archiveView":0,"follower":45655,"time":1662335524644},{"archiveView":0,"follower":45663,"time":1662450739377},{"archiveView":0,"follower":45699,"time":1662557569467},{"archiveView":0,"follower":45711,"time":1662672904757},{"archiveView":0,"follower":45751,"time":1662739396569},{"archiveView":0,"follower":45787,"time":1662796219487},{"archiveView":0,"follower":45823,"time":1662808821482},{"archiveView":0,"follower":45860,"time":1662815717824},{"archiveView":0,"follower":45980,"time":1662834749698}]